notebook_cleaner/__init__.py
notebook_cleaner/notebook_cleaner.py
notebook_cleaner-0.1.3.dist-info/DESCRIPTION.rst
notebook_cleaner-0.1.3.dist-info/METADATA
notebook_cleaner-0.1.3.dist-info/RECORD
notebook_cleaner-0.1.3.dist-info/WHEEL
notebook_cleaner-0.1.3.dist-info/entry_points.txt
notebook_cleaner-0.1.3.dist-info/metadata.json
notebook_cleaner-0.1.3.dist-info/top_level.txt
