Metadata-Version: 2.0
Name: notebook-cleaner
Version: 0.1.3
Summary: Remove code from HTML files rendered from Jupyter notebooks
Home-page: https://github.com/RAvdek/notebook_cleaner
Author: Russell Avdek
Author-email: russell.avdek@gmail.com
License: MIT
Keywords: ipython
Platform: UNKNOWN
Classifier: Development Status :: 4 - Beta
Classifier: Intended Audience :: Developers
Classifier: License :: OSI Approved :: MIT License
Classifier: Programming Language :: Python :: 2
Classifier: Programming Language :: Python :: 2.6
Classifier: Programming Language :: Python :: 2.7
Classifier: Programming Language :: Python :: 3
Classifier: Programming Language :: Python :: 3.2
Classifier: Programming Language :: Python :: 3.3
Classifier: Programming Language :: Python :: 3.4
Requires-Dist: beautifulsoup4
Requires-Dist: docopt
